MANIFEST.in
setup.py
docs/HISTORY.txt
src/dolmen/__init__.py
src/dolmen.content.egg-info/PKG-INFO
src/dolmen.content.egg-info/SOURCES.txt
src/dolmen.content.egg-info/dependency_links.txt
src/dolmen.content.egg-info/namespace_packages.txt
src/dolmen.content.egg-info/not-zip-safe
src/dolmen.content.egg-info/requires.txt
src/dolmen.content.egg-info/top_level.txt
src/dolmen/content/README.txt
src/dolmen/content/__init__.py
src/dolmen/content/base.py
src/dolmen/content/configure.zcml
src/dolmen/content/directives.py
src/dolmen/content/factoring.py
src/dolmen/content/interfaces.py
src/dolmen/content/meta.py
src/dolmen/content/meta.zcml
src/dolmen/content/utils.py
src/dolmen/content/tests/__init__.py
src/dolmen/content/tests/ftesting.zcml
src/dolmen/content/tests/test_package.py
src/dolmen/content/tests/factory/__init__.py
src/dolmen/content/tests/factory/auto_factory.py
src/dolmen/content/tests/factory/custom_factory.py
src/dolmen/content/tests/factory/no_factory.py
src/dolmen/content/tests/overview/__init__.py
src/dolmen/content/tests/overview/base.py
src/dolmen/content/tests/overview/contenttype.py
src/dolmen/content/tests/overview/simple.py
src/dolmen/content/tests/schema/__init__.py
src/dolmen/content/tests/schema/directive.py
src/dolmen/content/tests/schema/heritage.py
src/dolmen/content/tests/schema/initialize.py
src/dolmen/content/tests/schema/location.py
src/dolmen/content/tests/schema/multiple.py
src/dolmen/content/tests/schema/no_grokking.py
src/dolmen/content/tests/schema/preserve.py
src/dolmen/content/tests/schema/single.py