Metadata-Version: 1.0
Name: dolmen.content
Version: 0.7.1
Summary: Dolmen content type framework
Home-page: http://gitweb.dolmen-project.org/
Author: Souheil Chelfouh
Author-email: souheil@chelfouh.com
License: GPL
Keywords: Grok Zope3 CMS Dolmen Content
Platform: Any
Classifier: Environment :: Web Environment
Classifier: Framework :: Zope3
Classifier: Intended Audience :: Other Audience
Classifier: License :: OSI Approved :: GNU General Public License (GPL)
Classifier: Operating System :: OS Independent
Classifier: Programming Language :: Python
